whatsapp_business_api_client/__init__.py
whatsapp_business_api_client/api/__init__.py
whatsapp_business_api_client/api/application/__init__.py
whatsapp_business_api_client/api/application/delete_media_providers.py
whatsapp_business_api_client/api/application/get_application_settings.py
whatsapp_business_api_client/api/application/get_media_providers.py
whatsapp_business_api_client/api/application/reset_application_settings.py
whatsapp_business_api_client/api/application/set_shards.py
whatsapp_business_api_client/api/application/update_application_settings.py
whatsapp_business_api_client/api/backup_restore/__init__.py
whatsapp_business_api_client/api/backup_restore/backup_settings.py
whatsapp_business_api_client/api/backup_restore/restore_settings.py
whatsapp_business_api_client/api/business_profile/__init__.py
whatsapp_business_api_client/api/business_profile/get_business_profile.py
whatsapp_business_api_client/api/business_profile/update_business_profile.py
whatsapp_business_api_client/api/certificates/__init__.py
whatsapp_business_api_client/api/certificates/delete_webhook_ca_certificate.py
whatsapp_business_api_client/api/certificates/download_ca_certificate.py
whatsapp_business_api_client/api/certificates/download_webhook_ca_certificate.py
whatsapp_business_api_client/api/certificates/upload_certificate.py
whatsapp_business_api_client/api/certificates/upload_webhook_ca_certificate.py
whatsapp_business_api_client/api/contacts/__init__.py
whatsapp_business_api_client/api/contacts/check_contact.py
whatsapp_business_api_client/api/default/__init__.py
whatsapp_business_api_client/api/default/delete_profile_photo.py
whatsapp_business_api_client/api/groups/__init__.py
whatsapp_business_api_client/api/groups/create_group.py
whatsapp_business_api_client/api/groups/delete_group_icon.py
whatsapp_business_api_client/api/groups/delete_group_invite.py
whatsapp_business_api_client/api/groups/demote_group_admin.py
whatsapp_business_api_client/api/groups/get_all_groups.py
whatsapp_business_api_client-1.0.dist-info/entry_points.txt
whatsapp_business_api_client-1.0.dist-info/WHEEL
whatsapp_business_api_client-1.0.dist-info/METADATA
whatsapp_business_api_client-1.0.dist-info/RECORD
