Metadata-Version: 2.1
Name: whatsapp-business-api-client
Version: 1.0
Summary: A client library for accessing WhatsApp Business API
Requires-Python: >=3.6,<4.0
Classifier: Programming Language :: Python :: 3
Classifier: Programming Language :: Python :: 3.10
Classifier: Programming Language :: Python :: 3.6
Classifier: Programming Language :: Python :: 3.7
Classifier: Programming Language :: Python :: 3.8
Classifier: Programming Language :: Python :: 3.9
Requires-Dist: attrs (>=20.1.0,<22.0.0)
Requires-Dist: httpx (>=0.15.4,<0.22.0)
Requires-Dist: python-dateutil (>=2.8.0,<3.0.0)
